{
  "seasons": [
    {
      "air_date": "2021-03-14",
      "episode_count": "3",
      "id": 1001,
      "name": "Season 1",
      "overview": "",
      "season_number": 1,
      "cover": "http://cdn.example/covers/series-55-s1.jpg"
    },
    {
      "air_date": "2022-04-01",
      "episode_count": 2,
      "id": 1002,
      "name": "Season 2",
      "season_number": "2",
      "cover": ""
    }
  ],
  "info": {
    "name": "A Drama Series",
    "cover": "http://cdn.example/covers/series-55.jpg",
    "plot": "Someone does something, at length.",
    "cast": "A Person, Another Person",
    "genre": "Drama",
    "releaseDate": "2021-03-14",
    "rating": "8.1",
    "episode_run_time": "52",
    "category_id": "20"
  },
  "episodes": {
    "1": [
      {
        "id": "90001",
        "episode_num": 1,
        "title": "Pilot",
        "container_extension": "mkv",
        "season": 1,
        "info": {
          "movie_image": "http://cdn.example/stills/90001.jpg",
          "plot": "It begins.",
          "duration_secs": 3120,
          "duration": "00:52:00",
          "bitrate": 4200
        },
        "custom_sid": "",
        "added": "1704067200"
      },
      {
        "id": 90002,
        "episode_num": "2",
        "title": "The Second One",
        "container_extension": "mkv",
        "season": "1",
        "info": {
          "movie_image": "",
          "duration_secs": "3100"
        }
      },
      {
        "id": "90003",
        "episode_num": 3,
        "title": "",
        "season": 1,
        "info": []
      }
    ],
    "2": [
      {
        "id": "90004",
        "episode_num": 1,
        "title": "Return",
        "container_extension": "mp4",
        "season": 0,
        "info": {
          "movie_image": "http://cdn.example/stills/90004.jpg"
        }
      },
      {
        "id": "",
        "episode_num": 2,
        "title": "Unusable — No Episode Id",
        "season": 2
      }
    ]
  }
}
